yakstack.py
yakstack-1.2.0.dist-info/LICENSE.txt
yakstack-1.2.0.dist-info/METADATA
yakstack-1.2.0.dist-info/WHEEL
yakstack-1.2.0.dist-info/entry_points.txt
yakstack-1.2.0.dist-info/top_level.txt
yakstack-1.2.0.dist-info/RECORD
