Metadata-Version: 2.1
Name: yakstack
Version: 1.2.0
Summary: A command-line utility to help you stack your yaks.
Home-page: https://github.com/gilmoreorless/yakstack
Author: Gilmore Davidson
Author-email: gilmoreorless@gmail.com
License: MIT
Keywords: yak stack,yak frame,cli,tasks
Platform: UNKNOWN
Classifier: Development Status :: 5 - Production/Stable
Classifier: Environment :: Console
Classifier: Intended Audience :: Developers
Classifier: Topic :: Utilities
Classifier: License :: OSI Approved :: MIT License
Classifier: Programming Language :: Python :: 2
Classifier: Programming Language :: Python :: 2.7
Classifier: Programming Language :: Python :: 3
Classifier: Programming Language :: Python :: 3.5
License-File: LICENSE.txt
